<annotation verified="yes">
  <folder>JPEGImages</folder>
  <filename>000240</filename>
  <path>E:\VOC&#25968;&#25454;&#38598;\VOCtest_06-Nov-2007\VOCdevkit\VOC2007\JPEGImages\000240.jpg</path>
  <source>
    <database>Unknown</database>
  </source>
  <size>
    <width>500</width>
    <height>375</height>
    <depth>3</depth>
  </size>
  <segmented>0</segmented>
  <object>
    <name>person</name>
    <pose>Unspecified</pose>
    <truncated>0</truncated>
    <difficult>0</difficult>
    <bndbox>
      <xmin>348</xmin>
      <ymin>153</ymin>
      <xmax>374</xmax>
      <ymax>189</ymax>
    </bndbox>
  </object>
  <object>
    <name>person</name>
    <pose>Unspecified</pose>
    <truncated>0</truncated>
    <difficult>0</difficult>
    <bndbox>
      <xmin>159</xmin>
      <ymin>153</ymin>
      <xmax>175</xmax>
      <ymax>193</ymax>
    </bndbox>
  </object>
</annotation>
