<annotation verified="yes">
  <folder>JPEGImages</folder>
  <filename>005931</filename>
  <path>E:\VOC&#25968;&#25454;&#38598;\VOCtest_06-Nov-2007\VOCdevkit\VOC2007\JPEGImages\005931.jpg</path>
  <source>
    <database>Unknown</database>
  </source>
  <size>
    <width>500</width>
    <height>375</height>
    <depth>3</depth>
  </size>
  <segmented>0</segmented>
  <object>
    <name>person</name>
    <pose>Unspecified</pose>
    <truncated>0</truncated>
    <difficult>0</difficult>
    <bndbox>
      <xmin>322</xmin>
      <ymin>210</ymin>
      <xmax>359</xmax>
      <ymax>286</ymax>
    </bndbox>
  </object>
  <object>
    <name>person</name>
    <pose>Unspecified</pose>
    <truncated>0</truncated>
    <difficult>0</difficult>
    <bndbox>
      <xmin>128</xmin>
      <ymin>223</ymin>
      <xmax>160</xmax>
      <ymax>322</ymax>
    </bndbox>
  </object>
  <object>
    <name>person</name>
    <pose>Unspecified</pose>
    <truncated>0</truncated>
    <difficult>0</difficult>
    <bndbox>
      <xmin>193</xmin>
      <ymin>269</ymin>
      <xmax>231</xmax>
      <ymax>362</ymax>
    </bndbox>
  </object>
  <object>
    <name>person</name>
    <pose>Unspecified</pose>
    <truncated>0</truncated>
    <difficult>0</difficult>
    <bndbox>
      <xmin>242</xmin>
      <ymin>260</ymin>
      <xmax>274</xmax>
      <ymax>360</ymax>
    </bndbox>
  </object>
  <object>
    <name>person</name>
    <pose>Unspecified</pose>
    <truncated>0</truncated>
    <difficult>0</difficult>
    <bndbox>
      <xmin>401</xmin>
      <ymin>304</ymin>
      <xmax>439</xmax>
      <ymax>374</ymax>
    </bndbox>
  </object>
  <object>
    <name>person</name>
    <pose>Unspecified</pose>
    <truncated>1</truncated>
    <difficult>0</difficult>
    <bndbox>
      <xmin>455</xmin>
      <ymin>300</ymin>
      <xmax>489</xmax>
      <ymax>375</ymax>
    </bndbox>
  </object>
</annotation>
