<annotation verified="yes">
  <folder>JPEGImages</folder>
  <filename>003084</filename>
  <path>E:\VOC&#25968;&#25454;&#38598;\VOCtest_06-Nov-2007\VOCdevkit\VOC2007\JPEGImages\003084.jpg</path>
  <source>
    <database>Unknown</database>
  </source>
  <size>
    <width>500</width>
    <height>332</height>
    <depth>3</depth>
  </size>
  <segmented>0</segmented>
  <object>
    <name>person</name>
    <pose>Unspecified</pose>
    <truncated>0</truncated>
    <difficult>0</difficult>
    <bndbox>
      <xmin>222</xmin>
      <ymin>111</ymin>
      <xmax>259</xmax>
      <ymax>207</ymax>
    </bndbox>
  </object>
  <object>
    <name>person</name>
    <pose>Unspecified</pose>
    <truncated>0</truncated>
    <difficult>0</difficult>
    <bndbox>
      <xmin>139</xmin>
      <ymin>154</ymin>
      <xmax>165</xmax>
      <ymax>220</ymax>
    </bndbox>
  </object>
  <object>
    <name>person</name>
    <pose>Unspecified</pose>
    <truncated>0</truncated>
    <difficult>0</difficult>
    <bndbox>
      <xmin>94</xmin>
      <ymin>152</ymin>
      <xmax>110</xmax>
      <ymax>214</ymax>
    </bndbox>
  </object>
  <object>
    <name>person</name>
    <pose>Unspecified</pose>
    <truncated>0</truncated>
    <difficult>0</difficult>
    <bndbox>
      <xmin>68</xmin>
      <ymin>157</ymin>
      <xmax>86</xmax>
      <ymax>206</ymax>
    </bndbox>
  </object>
  <object>
    <name>person</name>
    <pose>Unspecified</pose>
    <truncated>0</truncated>
    <difficult>0</difficult>
    <bndbox>
      <xmin>361</xmin>
      <ymin>166</ymin>
      <xmax>385</xmax>
      <ymax>224</ymax>
    </bndbox>
  </object>
  <object>
    <name>person</name>
    <pose>Unspecified</pose>
    <truncated>0</truncated>
    <difficult>0</difficult>
    <bndbox>
      <xmin>413</xmin>
      <ymin>165</ymin>
      <xmax>433</xmax>
      <ymax>225</ymax>
    </bndbox>
  </object>
  <object>
    <name>person</name>
    <pose>Unspecified</pose>
    <truncated>0</truncated>
    <difficult>0</difficult>
    <bndbox>
      <xmin>458</xmin>
      <ymin>173</ymin>
      <xmax>486</xmax>
      <ymax>225</ymax>
    </bndbox>
  </object>
</annotation>
